PyPatt/PyPatt.py
PyPatt/__init__.py
pypatt-0.0.2.dist-info/LICENSE
pypatt-0.0.2.dist-info/METADATA
pypatt-0.0.2.dist-info/WHEEL
pypatt-0.0.2.dist-info/top_level.txt
pypatt-0.0.2.dist-info/RECORD
